git_diff_tool/__init__.py
git_diff_tool/diff_tool.py
git_diff_tool-1.0.0.dist-info/METADATA
git_diff_tool-1.0.0.dist-info/WHEEL
git_diff_tool-1.0.0.dist-info/entry_points.txt
git_diff_tool-1.0.0.dist-info/top_level.txt
git_diff_tool-1.0.0.dist-info/RECORD
