Metadata-Version: 2.1
Name: git-diff-tool
Version: 1.0.0
Summary: A tool for comparing Git branches
Home-page: https://github.com/kecheste/diff_tool
Author: Abenezer Tesfaye
Author-email: aben.ezer443@gmail.com
Classifier: Programming Language :: Python :: 3
Classifier: License :: OSI Approved :: MIT License
Classifier: Operating System :: OS Independent
Requires-Python: >=3.6
